fouriever/__init__.py
fouriever/average_oifits.py
fouriever/inst.py
fouriever/intercorr.py
fouriever/klcal.py
fouriever/plot.py
fouriever/util.py
fouriever/uvfit.py
fouriever/opticstools/__init__.py
fouriever/opticstools/opticstools.py
fouriever/opticstools/utils.py
fouriever-0.4.3.dist-info/METADATA
fouriever-0.4.3.dist-info/WHEEL
fouriever-0.4.3.dist-info/top_level.txt
fouriever-0.4.3.dist-info/RECORD
