Metadata-Version: 2.4
Name: fouriever
Version: 0.4.3
Summary: A single toolkit for calibrations, correlations, and companion search for kernel phase, aperture masking, and long-baseline interferometry data.
Author: Jens Kammerer
Project-URL: Homepage, https://github.com/kammerje/fouriever
Project-URL: Issues, https://github.com/kammerje/fouriever/issues
Requires-Dist: numpy
Requires-Dist: matplotlib
Requires-Dist: scipy
Requires-Dist: astropy
Requires-Dist: corner
Requires-Dist: emcee
Requires-Dist: pymultinest
Requires-Dist: mpmath
Provides-Extra: fft
Requires-Dist: pyFFTW; extra == "fft"
